nessus_file_analyzer/__about__.py
nessus_file_analyzer/__init__.py
nessus_file_analyzer/__main__.py
nessus_file_analyzer/_version.py
nessus_file_analyzer/app.py
nessus_file_analyzer/ico.py
nessus_file_analyzer/ico_generator.py
nessus_file_analyzer/utilities.py
nessus_file_analyzer/dialogs/__init__.py
nessus_file_analyzer/dialogs/about.py
nessus_file_analyzer/dialogs/update_check.py
nessus_file_analyzer/dialogs/url_open.py
nessus_file_analyzer/plugins/__init__.py
nessus_file_analyzer/plugins/base.py
nessus_file_analyzer/plugins/discovery.py
nessus_file_analyzer/ui/__init__.py
nessus_file_analyzer/ui/mainwindow.py
nessus_file_analyzer-0.12.5.dist-info/licenses/LICENSE
nessus_file_analyzer-0.12.5.dist-info/METADATA
nessus_file_analyzer-0.12.5.dist-info/WHEEL
nessus_file_analyzer-0.12.5.dist-info/entry_points.txt
nessus_file_analyzer-0.12.5.dist-info/top_level.txt
nessus_file_analyzer-0.12.5.dist-info/RECORD
