Metadata-Version: 2.4
Name: nessus_file_analyzer
Version: 0.12.5
Summary: nessus file analyzer (NFA) by LimberDuck is a GUI tool which enables you to parse nessus scan files from Tenable Nessus and Tenable Security Center, and exports results to a spreadsheet file for effortless analysis.
Home-page: https://github.com/LimberDuck/nessus-file-analyzer
Author: Damian Krawczyk
Author-email: damian.krawczyk@limberduck.org
License: GPLv3
Classifier: Programming Language :: Python :: 3.13
Classifier: Programming Language :: Python :: 3.12
Classifier: Programming Language :: Python :: 3.11
Classifier: Programming Language :: Python :: 3.10
Classifier: License :: OSI Approved :: GNU General Public License v3 (GPLv3)
Classifier: Operating System :: OS Independent
Classifier: Development Status :: 4 - Beta
Classifier: Environment :: X11 Applications :: Qt
Classifier: Operating System :: POSIX :: Linux
Classifier: Operating System :: Microsoft :: Windows
Classifier: Operating System :: MacOS
License-File: LICENSE
Requires-Dist: chardet>=5.2.0
Requires-Dist: nessus-file-reader>=0.7.2
Requires-Dist: nfa-plugin-software-enumeration>=0.1.2
Requires-Dist: PyQt5>=5.15.11
Requires-Dist: XlsxWriter>=3.2.5
Requires-Dist: packaging>=25.0
Requires-Dist: requests>=2.32.5
Dynamic: author
Dynamic: author-email
Dynamic: classifier
Dynamic: description
Dynamic: description-content-type
Dynamic: home-page
Dynamic: license
Dynamic: license-file
Dynamic: requires-dist
Dynamic: summary
